cadbuildr/__init__.py
cadbuildr-0.0.1.dist-info/LICENSE
cadbuildr-0.0.1.dist-info/METADATA
cadbuildr-0.0.1.dist-info/WHEEL
cadbuildr-0.0.1.dist-info/RECORD
